{
  "itemInfo": {
    "itemNumber": 5,
    "description": "ADJUSTMENT TO A PREVIOUS P. ORDER",
    "model": "",
    "itemCode": "P",
    "sellingUnit": "PSE",
    "sellingUnitLong": "PSEUDO ITEM",
    "onHandQty": 9,
    "cost": 0,
    "price": 1000000,
    "visualVrfRequired": "Y",
    "loadIdc": "CW",
    "npiLevel": "",
    "deptNum": 0,
    "upcQuantity": 1,
    "endecaImagePath": {
      "sm": "",
      "lg": "",
      "xl": ""
    },
    "endecaItemNum": "",
    "endecaPrice": "0.000000",
    "endecaModelId": "",
    "endecaRecordId": "",
    "endecaProductDescription": "",
    "endecaProductName": "",
    "validationStatus": "VRF_REQ",
    "validationCode": "The item needs to be visually verified",
    "nextAction": "",
    "actionCode": "",
    "itemType": "",
    "note": "",
    "combinable": 1,
    "discountable": 1,
    "message": "",
    "enableInstallSaleIdc": "",
    "endecaProductReviewCount": "",
    "endecaProductRating": "",
    "Locations": [],
    "workfile": "FSTLAN0224362",
    "lineNbr": -1,
    "paintFormula": ""
  }
}
